vector/__init__.py
classofvector2d-1.0.4.dist-info/LICENCE.txt
classofvector2d-1.0.4.dist-info/METADATA
classofvector2d-1.0.4.dist-info/WHEEL
classofvector2d-1.0.4.dist-info/top_level.txt
classofvector2d-1.0.4.dist-info/RECORD
