Metadata-Version: 2.1
Name: classofvector2d
Version: 1.0.4
Summary: Prepared to help graphics coding for Python
Home-page: https://github.com/mehmetrifatirmak/2D-Vector-Class
Author: Mehmet R. Irmak
Author-email: mehmet.r.river@gmail.com
License: UNKNOWN
Platform: UNKNOWN
Classifier: Programming Language :: Python :: 3
Classifier: License :: OSI Approved :: MIT License
Classifier: Operating System :: OS Independent
Classifier: Operating System :: Microsoft :: Windows :: Windows 10
Requires-Python: >=3.6
